{"./":{"url":"./","title":"Introduction","keywords":"","body":"My Englishnote introductionThis is winnerzr's Englishnote.It mainly show you some English skills,which was learned through studying.Welcome to star and fork.My Englishnote introduction This is winnerzr's Englishnote. It mainly show you some English skills,which was learned through studying. Welcome to star and fork. My hexo blog is Winnerzr. My github link Winnerzr. It is a book powered by GitBook. The software used in the experiment is English Your support is the driving force of my creation. © by Winnerzr all right reserved，powered by Gitbook该文档修订时间： 2020-10-21 09:19:43 "},"VocabularyAccumulation.html":{"url":"VocabularyAccumulation.html","title":"Vocabulary","keywords":"","body":" patent：专利 © by Winnerzr all right reserved，powered by Gitbook该文档修订时间： 2020-10-21 09:19:43 "},"ebook.html":{"url":"ebook.html","title":"ebook","keywords":"","body":"© by Winnerzr all right reserved，powered by Gitbook该文档修订时间： 2020-10-22 22:55:50 "},"The Three Musketeers.html":{"url":"The Three Musketeers.html","title":"The Three Musketeers","keywords":"","body":"© by Winnerzr all right reserved，powered by Gitbook该文档修订时间： 2020-10-22 23:20:38 "},"BritishEnglish.html":{"url":"BritishEnglish.html","title":"BritishEnglish","keywords":"","body":"© by Winnerzr all right reserved，powered by Gitbook该文档修订时间： 2020-10-21 09:19:43 "}}